grazie/__init__.py
grazie/_logger.py
grazie/db.py
grazie-0.1.2.dist-info/METADATA
grazie-0.1.2.dist-info/WHEEL
grazie-0.1.2.dist-info/RECORD
