Metadata-Version: 2.1
Name: grazie
Version: 0.1.2
Summary: prepare for data manipulate use
Author: Yue
Author-email: panyu996@outlook.com
Requires-Python: >=3.10,<4.0
Classifier: Programming Language :: Python :: 3
Classifier: Programming Language :: Python :: 3.10
Classifier: Programming Language :: Python :: 3.11
Classifier: Programming Language :: Python :: 3.12
Requires-Dist: sqlalchemy (>=2.0.35,<3.0.0)
